tb_go/__init__.py
tb_go/main.py
tb_go-1.2.4.dist-info/METADATA
tb_go-1.2.4.dist-info/WHEEL
tb_go-1.2.4.dist-info/entry_points.txt
tb_go-1.2.4.dist-info/top_level.txt
tb_go-1.2.4.dist-info/RECORD
