Metadata-Version: 2.4
Name: tb-go
Version: 1.2.4
Summary: Traceback go - Navigate to lines in tracebacks from the command-line
Author-email: "@readwithai" <talwrii@gmail.com>
Project-URL: Homepage, https://github.com/talwrii/tb-go
Requires-Python: >=3.8
